example_dsl_pkg/__init__.py
example_dsl_pkg/testMyPythonPKG.py
secondPKG/__init__.py
secondPKG/second.py
example_dsl_pkg-1.1.dist-info/METADATA
example_dsl_pkg-1.1.dist-info/WHEEL
example_dsl_pkg-1.1.dist-info/top_level.txt
example_dsl_pkg-1.1.dist-info/RECORD
