Metadata-Version: 2.1
Name: example-dsl-pkg
Version: 1.1
Summary: simple example
Home-page: UNKNOWN
Author: Du Shulin
Author-email: 986525775@qq.com
License: MIT License
Platform: UNKNOWN
Classifier: Programming Language :: Python :: 3
Classifier: License :: OSI Approved :: MIT License
Classifier: Operating System :: OS Independent
